disnakeSuperUtils/__init__.py
disnakeSuperUtils/antispam.py
disnakeSuperUtils/ban.py
disnakeSuperUtils/base.py
disnakeSuperUtils/birthday.py
disnakeSuperUtils/client.py
disnakeSuperUtils/commandhinter.py
disnakeSuperUtils/convertors.py
disnakeSuperUtils/database.py
disnakeSuperUtils/economy.py
disnakeSuperUtils/fivem.py
disnakeSuperUtils/imaging.py
disnakeSuperUtils/infractions.py
disnakeSuperUtils/invitetracker.py
disnakeSuperUtils/kick.py
disnakeSuperUtils/leveling.py
disnakeSuperUtils/messagefilter.py
disnakeSuperUtils/modmail.py
disnakeSuperUtils/mute.py
disnakeSuperUtils/paginator.py
disnakeSuperUtils/prefix.py
disnakeSuperUtils/punishments.py
disnakeSuperUtils/reactionroles.py
disnakeSuperUtils/spotify.py
disnakeSuperUtils/template.py
disnakeSuperUtils/twitch.py
disnakeSuperUtils/youtube.py
disnakeSuperUtils/assets/1.png
disnakeSuperUtils/assets/2.png
disnakeSuperUtils/assets/3.png
disnakeSuperUtils/assets/dnd.png
disnakeSuperUtils/assets/font.ttf
disnakeSuperUtils/assets/idle.png
disnakeSuperUtils/assets/offline.png
disnakeSuperUtils/assets/online.png
disnakeSuperUtils/assets/spotify_black.png
disnakeSuperUtils/assets/spotify_white.png
disnakeSuperUtils/assets/streaming.png
disnakeSuperUtils/music/__init__.py
disnakeSuperUtils/music/constants.py
disnakeSuperUtils/music/enums.py
disnakeSuperUtils/music/exceptions.py
disnakeSuperUtils/music/music.py
disnakeSuperUtils/music/player.py
disnakeSuperUtils/music/playlist.py
disnakeSuperUtils/music/queue.py
disnakeSuperUtils/music/utils.py
disnakeSuperUtils/music/lavalink/__init__.py
disnakeSuperUtils/music/lavalink/equalizer.py
disnakeSuperUtils/music/lavalink/lavalink.py
disnakeSuperUtils/music/lavalink/player.py
disnakeSuperUtils-0.9.2.dist-info/LICENSE
disnakeSuperUtils-0.9.2.dist-info/METADATA
disnakeSuperUtils-0.9.2.dist-info/WHEEL
disnakeSuperUtils-0.9.2.dist-info/top_level.txt
disnakeSuperUtils-0.9.2.dist-info/RECORD
