Metadata-Version: 2.1
Name: disnakeSuperUtils
Version: 0.9.2
Summary: Discord Bot Development made easy!
Home-page: https://github.com/Ariz-z/disnake-super-utils.git
Download-URL: https://github.com/Ariz-z/disnake-super-utils/archive/refs/tags/v0.3.0.tar.gz
Author: koyashie07, adam7100 and Ariz0001
License: MIT
Keywords: discord,easy,disnake,music,download,links,images,videos,audio,bot,paginator,economy,reaction,reaction roles,database,database manager
Platform: UNKNOWN
Classifier: Development Status :: 4 - Beta
Classifier: Intended Audience :: Developers
Classifier: Topic :: Software Development :: Build Tools
Classifier: License :: OSI Approved :: MIT License
Classifier: Programming Language :: Python :: 3
Classifier: Programming Language :: Python :: 3.4
Classifier: Programming Language :: Python :: 3.5
Classifier: Programming Language :: Python :: 3.6
License-File: LICENSE
Requires-Dist: disnake
Requires-Dist: Pillow
Requires-Dist: requests
Requires-Dist: spotipy
Requires-Dist: aiosqlite
Requires-Dist: motor
Requires-Dist: aiopg
Requires-Dist: aiomysql
Requires-Dist: discord-components
Requires-Dist: pytz
Requires-Dist: wavelink
Requires-Dist: youtube-dl
